{
    "name": "Anggotas",
    "fields": [
        {
            "fieldName": "nama",
            "fieldType": "String",
            "fieldValidateRules": [
                "required"
            ]
        }
    ],
    "relationships": [],
    "changelogDate": "20191028103626",
    "entityTableName": "anggotas",
    "dto": "no",
    "pagination": "no",
    "service": "no",
    "jpaMetamodelFiltering": false,
    "fluentMethods": true,
    "readOnly": false,
    "clientRootFolder": "",
    "applications": "*"
}